basicsr/VERSION
basicsr/__init__.py
basicsr/setup.py
basicsr/train.py
basicsr/version.py
basicsr/archs/__init__.py
basicsr/archs/arcface_arch.py
basicsr/archs/arch_util.py
basicsr/archs/codeformer_arch.py
basicsr/archs/rrdbnet_arch.py
basicsr/archs/vgg_arch.py
basicsr/archs/vqgan_arch.py
basicsr/data/__init__.py
basicsr/data/data_sampler.py
basicsr/data/data_util.py
basicsr/data/prefetch_dataloader.py
basicsr/data/transforms.py
basicsr/losses/__init__.py
basicsr/losses/loss_util.py
basicsr/losses/losses.py
basicsr/metrics/__init__.py
basicsr/metrics/metric_util.py
basicsr/metrics/psnr_ssim.py
basicsr/models/__init__.py
basicsr/ops/__init__.py
basicsr/ops/dcn/__init__.py
basicsr/ops/dcn/deform_conv.py
basicsr/ops/dcn/src/deform_conv_cuda.cpp
basicsr/ops/dcn/src/deform_conv_cuda_kernel.cu
basicsr/ops/dcn/src/deform_conv_ext.cpp
basicsr/ops/fused_act/__init__.py
basicsr/ops/fused_act/fused_act.py
basicsr/ops/fused_act/src/fused_bias_act.cpp
basicsr/ops/fused_act/src/fused_bias_act_kernel.cu
basicsr/ops/upfirdn2d/__init__.py
basicsr/ops/upfirdn2d/upfirdn2d.py
basicsr/ops/upfirdn2d/src/upfirdn2d.cpp
basicsr/ops/upfirdn2d/src/upfirdn2d_kernel.cu
basicsr/utils/__init__.py
basicsr/utils/dist_util.py
basicsr/utils/download_util.py
basicsr/utils/file_client.py
basicsr/utils/img_util.py
basicsr/utils/lmdb_util.py
basicsr/utils/logger.py
basicsr/utils/matlab_functions.py
basicsr/utils/misc.py
basicsr/utils/options.py
basicsr/utils/realesrgan_utils.py
basicsr/utils/registry.py
basicsr/utils/video_util.py
codeformer/.gitignore
codeformer/LICENSE
codeformer/README.md
codeformer/__init__.py
codeformer/inference_codeformer.py
codeformer/lib.py
codeformer/requirements.txt
codeformer/basicsr/VERSION
codeformer/basicsr/__init__.py
codeformer/basicsr/setup.py
codeformer/basicsr/train.py
codeformer/basicsr/version.py
codeformer/basicsr/archs/__init__.py
codeformer/basicsr/archs/arcface_arch.py
codeformer/basicsr/archs/arch_util.py
codeformer/basicsr/archs/codeformer_arch.py
codeformer-0.0.11.dist-info/LICENSE
codeformer-0.0.11.dist-info/METADATA
codeformer-0.0.11.dist-info/WHEEL
codeformer-0.0.11.dist-info/top_level.txt
codeformer-0.0.11.dist-info/RECORD
